commercetools/__init__.py
commercetools/base_client.py
commercetools/client.py
commercetools/constants.py
commercetools/exceptions.py
commercetools/helpers.py
commercetools/paginators.py
commercetools/predicates.py
commercetools/protocols.py
commercetools/py.typed
commercetools/types.py
commercetools/typing.py
commercetools/utils.py
commercetools/version.py
commercetools/checkout/__init__.py
commercetools/checkout/client/__init__.py
commercetools/checkout/models/__init__.py
commercetools/checkout/models/_abstract.py
commercetools/checkout/models/responses.py
commercetools/checkout/models/_schemas/responses.py
commercetools/contrib/__init__.py
commercetools/contrib/pytest.py
commercetools/frontend/__init__.py
commercetools/frontend/client/__init__.py
commercetools/frontend/client/action/__init__.py
commercetools/frontend/client/action/frontastic_action_by_namespace_by_action_request_builder.py
commercetools/frontend/client/action/frontastic_action_request_builder.py
commercetools/frontend/client/context/__init__.py
commercetools/frontend/client/context/frontastic_context_request_builder.py
commercetools/frontend/client/data_source/__init__.py
commercetools/frontend/client/data_source/frontastic_data_source_by_identifier_request_builder.py
commercetools/frontend/client/data_source/frontastic_data_source_request_builder.py
commercetools/frontend/client/frontastic/__init__.py
commercetools/frontend/client/frontastic/frontastic_request_builder.py
commercetools/frontend/client/page/__init__.py
commercetools/frontend/client/page/frontastic_page_request_builder.py
commercetools/frontend/client/preview/__init__.py
commercetools/frontend/client/preview/frontastic_preview_request_builder.py
commercetools/frontend/models/__init__.py
commercetools/frontend/models/_abstract.py
commercetools/frontend/models/common.py
commercetools/frontend/models/_schemas/common.py
commercetools/importapi/__init__.py
commercetools/importapi/client/__init__.py
commercetools-2023.6.29.dist-info/LICENSE
commercetools-2023.6.29.dist-info/METADATA
commercetools-2023.6.29.dist-info/WHEEL
commercetools-2023.6.29.dist-info/top_level.txt
commercetools-2023.6.29.dist-info/RECORD
