Metadata-Version: 2.1
Name: commercetools
Version: 2023.6.29
Summary: SDK for Commercetools
Home-page: https://github.com/labd/commercetools-python-sdk
Author: Lab Digital B.V.
Author-email: opensource@labdigital.nl
License: MIT
Classifier: Development Status :: 5 - Production/Stable
Classifier: License :: OSI Approved :: MIT License
Classifier: Programming Language :: Python :: 3
Classifier: Programming Language :: Python :: 3.8
Classifier: Programming Language :: Python :: 3.9
Classifier: Programming Language :: Python :: 3.10
Classifier: Programming Language :: Python :: 3.10
Classifier: Programming Language :: Python :: Implementation :: CPython
Provides-Extra: docs
Provides-Extra: test
License-File: LICENSE
